{
  "$schema": "http://json-schema.org/draft-04/schema#",
  "type": "object",
  "additionalProperties": false,
  "required": [
    "body",
    "first_public_at"
  ],
  "properties": {
    "body": {
      "type": "string"
    },
    "image": {
      "$ref": "#/definitions/image"
    },
    "format_display_type": {
      "type": "string",
      "enum": [
        "case_study"
      ]
    },
    "first_public_at": {
      "type": "string",
      "format": "date-time"
    },
    "change_note": {
      "anyOf": [
        {
          "type": "string"
        },
        {
          "type": "null"
        }
      ]
    },
    "change_history": {
      "$ref": "#/definitions/change_history"
    },
    "tags": {
      "type": "object",
      "additionalProperties": false,
      "properties": {
        "browse_pages": {
          "type": "array",
          "items": {
            "type": "string"
          }
        },
        "topics": {
          "type": "array",
          "items": {
            "type": "string"
          }
        },
        "policies": {
          "type": "array",
          "items": {
            "type": "string"
          }
        }
      }
    },
    "withdrawn_notice": {
      "$ref": "#/definitions/withdrawn_notice"
    },
    "archive_notice": {
      "type": "object",
      "additionalProperties": false,
      "properties": {
        "explanation": {
          "type": "string"
        },
        "archived_at": {
          "format": "date-time"
        }
      }
    },
    "emphasised_organisations": {
      "$ref": "#/definitions/emphasised_organisations"
    }
  }
}
