{
  "$schema": "http://json-schema.org/draft-04/schema#",
  "type": "object",
  "additionalProperties": false,
  "properties": {
    "internal_name": {
      "type": "string",
      "description": "An internal name for admin interfaces. Includes parent."
    },
    "second_level_ordering": {
      "enum": [ "alphabetical", "curated" ]
    },
    "ordered_second_level_browse_pages": {
      "description": "All 2nd level browse pages under active_top_level_browse_page, with ordering preserved",
      "$ref": "#/definitions/guid_list"
    },
    "groups": {
      "type": "array",
      "items": {
        "type": "object",
        "additionalProperties": false,
        "required": [
          "name",
          "contents"
        ],
        "properties": {
          "name": {
            "type": "string"
          },
          "contents": {
            "type": "array",
            "items": {
              "$ref" : "#/definitions/absolute_path"
            }
          }
        }
      }
    }
  }
}
